flake8_network_timeout.py
flake8_network_timeout-0.2.0.dist-info/DESCRIPTION.rst
flake8_network_timeout-0.2.0.dist-info/METADATA
flake8_network_timeout-0.2.0.dist-info/RECORD
flake8_network_timeout-0.2.0.dist-info/WHEEL
flake8_network_timeout-0.2.0.dist-info/entry_points.txt
flake8_network_timeout-0.2.0.dist-info/metadata.json
flake8_network_timeout-0.2.0.dist-info/top_level.txt
