Metadata-Version: 2.0
Name: flake8-network-timeout
Version: 0.2.0
Summary: our extension to flake8
Home-page: https://gitlab.com/messense/flake8-network-timeout
Author: Messense Lv
Author-email: messense@icloud.com
License: MIT
Platform: UNKNOWN
Classifier: Framework :: Flake8
Classifier: Environment :: Console
Classifier: Intended Audience :: Developers
Classifier: License :: OSI Approved :: MIT License
Classifier: Programming Language :: Python
Classifier: Programming Language :: Python :: 2
Classifier: Programming Language :: Python :: 3
Classifier: Topic :: Software Development :: Libraries :: Python Modules
Classifier: Topic :: Software Development :: Quality Assurance
Requires-Dist: flake8 (>3.0.0)
